trade_database_manager/__init__.py
trade_database_manager/config.py
trade_database_manager/core/__init__.py
trade_database_manager/core/typedefs.py
trade_database_manager/core/kdb/__init__.py
trade_database_manager/core/kdb/kdbmanager.py
trade_database_manager/core/kdb/qscripts/q.q
trade_database_manager/core/sql/__init__.py
trade_database_manager/core/sql/sqlmanager.py
trade_database_manager/core/sql/sqlreader.py
trade_database_manager/core/sql/sqlwriter.py
trade_database_manager/core/sql/utils.py
trade_database_manager/manager/__init__.py
trade_database_manager/manager/fields_data_type.py
trade_database_manager/manager/metadata_sql.py
trade_database_manager/manager/metadata_sql_cb.py
trade_database_manager/manager/metadata_sql_fut.py
trade_database_manager/manager/typedefs.py
trade_database_manager-0.0.12.dist-info/licenses/LICENSE
trade_database_manager-0.0.12.dist-info/METADATA
trade_database_manager-0.0.12.dist-info/WHEEL
trade_database_manager-0.0.12.dist-info/top_level.txt
trade_database_manager-0.0.12.dist-info/RECORD
