Metadata-Version: 2.4
Name: trade_database_manager
Version: 0.0.12
Summary: A wrapper of kdb and sql for convenient trade data management.
Author-email: YQ Cui <qianyun210603@hotmail.com>
License-Expression: MIT
Classifier: Operating System :: POSIX :: Linux
Classifier: Operating System :: Microsoft :: Windows
Classifier: Development Status :: 3 - Alpha
Classifier: Intended Audience :: Developers
Classifier: Programming Language :: Python :: 3
Classifier: Programming Language :: Python :: 3.10
Classifier: Programming Language :: Python :: 3.11
Classifier: Programming Language :: Python :: 3.12
Requires-Python: >=3.10
License-File: LICENSE
Requires-Dist: pandas>=2.0.0
Requires-Dist: numpy
Requires-Dist: ruamel.yaml
Requires-Dist: sqlalchemy
Requires-Dist: psycopg2
Provides-Extra: dev
Requires-Dist: ruff>=0.0.263; extra == "dev"
Requires-Dist: setuptools_scm>=8; extra == "dev"
Requires-Dist: setuptools>=64; extra == "dev"
Requires-Dist: wheel; extra == "dev"
Dynamic: license-file
